{
    "items": [
        {
            "title": "Celtic fans protest 'repression' outside Glasgow police station",
            "date": "2025-03-29 18:10",
            "feed_title": "GlasgowLive - Celtic FC",
            "link": "https:\/\/www.glasgowlive.co.uk\/news\/glasgow-news\/celtic-fans-protest-repression-outside-31310702",
            "site_title": null,
            "description": "Ultras were spotted on Saturday afternoon outside London Road Police Station with signs reading 'fans against criminalisation'. It comes after the group claimed that officers showed 'criminalisation' and 'repression' against Hoops fans earlier this month.",
            "enclosure_url": "https:\/\/i2-prod.glasgowlive.co.uk\/incoming\/article31310708.ece\/ALTERNATES\/s615\/0_Capture-14PNG.png",
            "width": 615,
            "height": 409
        },
        {
            "title": "Daizen Maeda brace helps\u00a0Celtic\u00a0to comfortable win over Hearts",
            "date": "2025-03-29 18:08",
            "feed_title": "Latest Celtic F.C. News | News, updates, and analysis related to Celtic Football Club. | STV News",
            "link": "https:\/\/news.stv.tv\/sport\/football\/daizen-maeda-brace-helps-celtic-to-comfortable-win-over-hearts",
            "site_title": null,
            "description": "Maeda netted either side of Jota\u2019s strike as\u00a0Celtic\u00a0edged closer to securing their fourth consecutive William Hill Premiership title.",
            "enclosure_url": "https:\/\/news.stv.tv\/wp-content\/uploads\/2025\/03\/d0480b31f9263ad89848cb73c1c884d5-1743271601-1221x720.jpg",
            "width": 1221,
            "height": 720
        },
        {
            "title": "Celtic player ratings vs Hearts: Three 'magic' 8\/10s, Maeda hits 30 goal mark as Hoops edge closer to title",
            "date": "2025-03-29 17:14",
            "feed_title": "GlasgowWorld Celtic",
            "link": "https:\/\/www.glasgowworld.com\/sport\/football\/celtic\/celtic-player-ratings-vs-hearts-three-magic-810s-maeda-hits-30-goal-mark-as-hoops-edge-closer-to-title-5053736",
            "site_title": null,
            "description": "How the Celtic players rated in the 3-0 victory over Hearts in the Scottish Premiership at Parkhead on Saturday afternoon",
            "enclosure_url": "https:\/\/www.glasgowworld.com\/jpim-static\/image\/2025\/03\/29\/17\/07\/GettyImages-2207495688.jpeg?width=1200&amp;auto=webp&amp;crop=3:2",
            "width": 1200,
            "height": 800
        },
        {
            "title": "Daizen Maeda is deadly Celtic dominator but that isn't the whole story as Hearts broken \u2013 3 talking points",
            "date": "2025-03-29 17:08",
            "feed_title": "Daily Record - Celtic FC",
            "link": "https:\/\/www.dailyrecord.co.uk\/sport\/football\/maeda-celtic-hearts-talking-points-34957554",
            "site_title": null,
            "description": "The Parkhead hitman took his season tally to 30 goals in his 150th appearance for the club",
            "enclosure_url": "https:\/\/i2-prod.dailyrecord.co.uk\/sport\/football\/article34957441.ece\/ALTERNATES\/s615\/0_JS364361433-1.jpg",
            "width": 615,
            "height": 409
        },
        {
            "title": "Wanyama\u2019s return to Scottish football ends in red card as Dunfermline thrashed by Ayr",
            "date": "2025-03-29 17:06",
            "feed_title": "Glasgow Times | Celtic",
            "link": "https:\/\/www.glasgowtimes.co.uk\/sport\/25048222.disaster-strikes-lennon-wanyama-sees-red-dunfermline-debut\/?ref=rss",
            "site_title": null,
            "description": "Victor Wanyama's return to Scottish football ended in disaster.",
            "enclosure_url": "https:\/\/www.glasgowtimes.co.uk\/resources\/images\/19266160\/?x=0&amp;y=0&amp;w=2400&amp;h=1350",
            "width": 2400,
            "height": 1545
        },
        {
            "title": "Victor Wanyama suffers disastrous Dunfermline RED CARD as Celtic hero sees Lennon publicly backs him with gesture",
            "date": "2025-03-29 17:04",
            "feed_title": "Daily Record - Celtic FC",
            "link": "https:\/\/www.dailyrecord.co.uk\/sport\/football\/football-news\/victor-wanyama-suffers-disastrous-dunfermline-34957524",
            "site_title": null,
            "description": "The Celtic hero earned an applause from Pars boss despite his indiscretion",
            "enclosure_url": "https:\/\/i2-prod.dailyrecord.co.uk\/sport\/football\/football-news\/article34957530.ece\/ALTERNATES\/s615\/0_unnamed.png",
            "width": 615,
            "height": 409
        },
        {
            "title": "Celtic 3 Hearts 0: Daizen Maeda hits 30 goal mark as champions edge closer to title",
            "date": "2025-03-29 16:58",
            "feed_title": "Glasgow Times | Celtic",
            "link": "https:\/\/www.glasgowtimes.co.uk\/sport\/25048207.celtic-3-hearts-0-instant-reaction-burning-issues\/?ref=rss",
            "site_title": null,
            "description": "Daizen Maeda netted a double and took his tally for Celtic this season to 30 as the Scottish champions beat Hearts 3-0 at home in the Premiership today.",
            "enclosure_url": "https:\/\/www.glasgowtimes.co.uk\/resources\/images\/19265983\/",
            "width": 2000,
            "height": 1333
        },
        {
            "title": "Celtic fans gather in strength after Old Firm incident as they show Police what they really think after serious claim",
            "date": "2025-03-29 16:30",
            "feed_title": "GlasgowWorld Celtic",
            "link": "https:\/\/www.glasgowworld.com\/sport\/football\/celtic\/celtic-fans-police-protest-glasgow-hearts-premiership-5057767",
            "site_title": null,
            "description": "The demonstration was organised by Celtic ultras group, The Green Brigade in response to \u2018criminalisation\u2019 ",
            "enclosure_url": "https:\/\/www.glasgowworld.com\/jpim-static\/image\/2025\/03\/25\/12\/05\/21329554.jpeg?width=1200&amp;auto=webp&amp;crop=3:2",
            "width": 1200,
            "height": 750
        },
        {
            "title": "Celtic supporters protest outside police station amid concerns over treatment of fans",
            "date": "2025-03-29 15:18",
            "feed_title": "Glasgow Times | Celtic",
            "link": "https:\/\/www.glasgowtimes.co.uk\/sport\/25048103.celtic-supporters-protest-outside-glasgow-police-station\/?ref=rss",
            "site_title": null,
            "description": "A SECTION of Celtic supporters protested outside a Glasgow police station\u00a0ahead of the clubs match against Hearts.",
            "enclosure_url": "https:\/\/www.glasgowtimes.co.uk\/resources\/images\/19266005\/",
            "width": 1200,
            "height": 800
        },
        {
            "title": "Celtic fans protest cops outside Glasgow police station",
            "date": "2025-03-29 15:17",
            "feed_title": "Daily Record - Celtic FC",
            "link": "https:\/\/www.dailyrecord.co.uk\/news\/scottish-news\/celtic-fans-protest-cops-outside-34957001",
            "site_title": null,
            "description": "A total of 90 fans were denied entry to Celtic park after refusing to be searched by police before the Old Firm on March 16.",
            "enclosure_url": "https:\/\/i2-prod.dailyrecord.co.uk\/incoming\/article34957090.ece\/ALTERNATES\/s615\/0_CapturePNG.png",
            "width": 615,
            "height": 409
        },
        {
            "title": "Brendan Rodgers has \u2018no problems\u2019 continuing with Maik Nawrocki in Celtic defence",
            "date": "2025-03-29 14:44",
            "feed_title": "Glasgow Times | Celtic",
            "link": "https:\/\/www.glasgowtimes.co.uk\/sport\/25048054.rodgers-no-problems-continuing-nawrocki-celtic-defence\/?ref=rss",
            "site_title": null,
            "description": "Brendan Rodgers has \u2018no problems\u2019 continuing with Maik Nawrocki in Celtic defence",
            "enclosure_url": "https:\/\/www.glasgowtimes.co.uk\/resources\/images\/19265819\/?x=19&amp;y=0&amp;w=2185&amp;h=1229",
            "width": 2400,
            "height": 1229
        },
        {
            "title": "Celtic mad schoolboy who went viral for \u2018beautiful\u2019 video invited to Switzerland",
            "date": "2025-03-29 14:34",
            "feed_title": "GlasgowLive - Celtic FC",
            "link": "https:\/\/www.glasgowlive.co.uk\/news\/glasgow-news\/celtic-mad-schoolboy-who-went-31288415",
            "site_title": null,
            "description": "It comes after we reported how the Elderslie youngster, who has been attending games with his dad since he was five years old, shared a 'special moment' with fans following the Hoops UEFA Champions League match at Parkhead.",
            "enclosure_url": "https:\/\/i2-prod.glasgowlive.co.uk\/incoming\/article31309521.ece\/ALTERNATES\/s615\/0_Screenshot-115-1.png",
            "width": 615,
            "height": 409
        },
        {
            "title": "Storied Scottish football club puts 135 years of history on the line - but it's not all rosy amid drum row",
            "date": "2025-03-29 14:28",
            "feed_title": "The Scotsman Celtic",
            "link": "https:\/\/www.scotsman.com\/sport\/football\/scottish-championship\/storied-scottish-football-club-puts-135-years-of-history-on-the-line-but-its-not-all-rosy-amid-drum-row-5057526",
            "site_title": null,
            "description": "Queen\u2019s Park are back in a cup final but ambitious club has slumped since that day at Rangers",
            "enclosure_url": "https:\/\/www.scotsman.com\/jpim-static\/image\/2025\/03\/28\/19\/05\/21339442.jpeg?width=1200&amp;auto=webp&amp;crop=3:2",
            "width": 1200,
            "height": 831
        },
        {
            "title": "Brown vs Lennon: Former Celtic teammates meet as Wanyama call made",
            "date": "2025-03-29 13:24",
            "feed_title": "Glasgow Times | Celtic",
            "link": "https:\/\/www.glasgowtimes.co.uk\/sport\/25047949.ex-celtic-teammates-meet-second-tier-wanyama-starts-bench\/?ref=rss",
            "site_title": null,
            "description": "All eyes are on the surprise Celtic reunion at Somerset Park this afternoon.",
            "enclosure_url": "https:\/\/www.glasgowtimes.co.uk\/resources\/images\/19265639\/?x=0&amp;y=24&amp;w=2400&amp;h=1350",
            "width": 2400,
            "height": 2561
        },
        {
            "title": "Brendan Rodgers reveals Celtic's strategy for signing Viljami Sinisalo",
            "date": "2025-03-29 13:10",
            "feed_title": "Glasgow Times | Celtic",
            "link": "https:\/\/www.glasgowtimes.co.uk\/sport\/25047934.brendan-rodgers-reveals-celtics-strategy-signing-viljami-sinisalo\/?ref=rss",
            "site_title": null,
            "description": "Brendan Rodgers reveals Celtic's strategy for signing Viljami Sinisalo",
            "enclosure_url": "https:\/\/www.glasgowtimes.co.uk\/resources\/images\/19265604\/?x=0&amp;y=0&amp;w=2400&amp;h=1350",
            "width": 2400,
            "height": 1555
        },
        {
            "title": "Celtic 3 Hearts 0 LIVE reaction as Hoops cruise closer to title with easy Parkhead win",
            "date": "2025-03-29 12:58",
            "feed_title": "Daily Record - Celtic FC",
            "link": "https:\/\/www.dailyrecord.co.uk\/sport\/football\/football-news\/celtic-vs-hearts-live-score-34956214",
            "site_title": null,
            "description": "It was easy street for Celtic as a double from Daizen Maeda either side of a Jota strike sealed a straightforward win",
            "enclosure_url": "https:\/\/i2-prod.dailyrecord.co.uk\/incoming\/article34741633.ece\/ALTERNATES\/s615\/0_Celtic-FC-v-Dundee-United-FC-William-Hill-Premiership.jpg",
            "width": 615,
            "height": 409
        },
        {
            "title": "The instant Celtic reaction to Rangers sickener revealed as former \u00a37m man set for emotional comeback \u2013 Parkhead bulletin",
            "date": "2025-03-29 11:20",
            "feed_title": "Daily Record - Celtic FC",
            "link": "https:\/\/www.dailyrecord.co.uk\/sport\/football\/instant-celtic-reaction-rangers-sickener-34956125",
            "site_title": null,
            "description": "Celtic are out to bounce back to that defeat against Rangers this afternoon",
            "enclosure_url": "https:\/\/i2-prod.dailyrecord.co.uk\/incoming\/article34862004.ece\/ALTERNATES\/s615\/0_Celtic-FC-Media-Access.jpg",
            "width": 615,
            "height": 409
        },
        {
            "title": "Watch forgotten Celtic loanee at his creative best with two classy assists",
            "date": "2025-03-29 10:17",
            "feed_title": "Glasgow Times | Celtic",
            "link": "https:\/\/www.glasgowtimes.co.uk\/sport\/25047775.watch-celtic-loanee-best-two-classy-assists\/?ref=rss",
            "site_title": null,
            "description": "Forgotten Celtic loanee Marco Tilio put in a standout performance as Melbourne City defeated Sydney FC 3-2 early this morning.",
            "enclosure_url": "https:\/\/www.glasgowtimes.co.uk\/resources\/images\/19265323\/",
            "width": 1081,
            "height": 556
        },
        {
            "title": "Victor Wanyama outlines Celtic 'hope' ahead of potential Dunfermline debut",
            "date": "2025-03-29 09:55",
            "feed_title": "Glasgow Times | Celtic",
            "link": "https:\/\/www.glasgowtimes.co.uk\/sport\/25047762.wanyama-outlines-celtic-hope-ahead-potential-pars-bow\/?ref=rss",
            "site_title": null,
            "description": "Victor Wanyama hopes to see some Celtic supporters in attendance as Dunfermline face Ayr United today.",
            "enclosure_url": "https:\/\/www.glasgowtimes.co.uk\/resources\/images\/19265300\/",
            "width": 2400,
            "height": 1583
        },
        {
            "title": "Brendan Rodgers names Celtic team to face Hearts with fringe man set for league debut",
            "date": "2025-03-29 09:02",
            "feed_title": "Glasgow Times | Celtic",
            "link": "https:\/\/www.glasgowtimes.co.uk\/sport\/25047701.brendan-rodgers-names-celtic-team-hearts-league-clash\/?ref=rss",
            "site_title": null,
            "description": "Celtic manager Brendan Rodgers has named his team to face Heart of Midlothian this afternoon.",
            "enclosure_url": "https:\/\/www.glasgowtimes.co.uk\/resources\/images\/19265235\/?x=0&amp;y=53&amp;w=2400&amp;h=1350",
            "width": 2400,
            "height": 1495
        }
    ]
}