{
    "items": [
        {
            "title": "Barry Ferguson's Rangers feat emulates legendary manager's start v Celtic over three decades ago",
            "date": "2025-03-17 22:00",
            "feed_title": "The Scotsman Celtic",
            "link": "https:\/\/www.scotsman.com\/sport\/football\/rangers\/barry-fergusons-rangers-feat-emulates-legendary-managers-start-v-celtic-over-three-decades-ago-5038165",
            "site_title": null,
            "description": "Ibrox interim manager enjoying stirring first few weeks in job",
            "enclosure_url": "https:\/\/www.scotsman.com\/webimg\/b25lY21zOmMxYjdlZGZmLWM4Y2ItNGNlMC1hMDQ3LWQyMzZjYjhlZjM3YTphYWNmYzQ4Yy01NWI2LTQzYjktYjJjOC1hNTUxZTQ0NWU5ZDY=.jpg?width=600&amp;auto=webp&amp;crop=3:2&amp;quality=70",
            "width": 600,
            "height": 399
        },
        {
            "title": "Aberdeen's Gothenburg Greats receive special gift as Clive Tyldesley pays unique tribute to the side who ruled Europe",
            "date": "2025-03-17 21:30",
            "feed_title": "Daily Record - Celtic FC",
            "link": "https:\/\/www.dailyrecord.co.uk\/sport\/football\/football-news\/aberdeen-clive-tyldesley-rangers-gothenburg-34879703",
            "site_title": null,
            "description": "The Reds famously defeated Real Madrid to lift the European Cup Winners' Cup 42 years ago",
            "enclosure_url": "https:\/\/i2-prod.dailyrecord.co.uk\/incoming\/article12519275.ece\/ALTERNATES\/s615\/0_JS16611491.jpg",
            "width": 615,
            "height": 409
        },
        {
            "title": "'Nonsense': Sutton hits out at Vaclav Cerny for 'silly' Celtic fan incident",
            "date": "2025-03-17 21:15",
            "feed_title": "Glasgow Times | Celtic",
            "link": "https:\/\/www.glasgowtimes.co.uk\/sport\/25015507.sutton-hits-cerny-silly-celtic-fan-incident\/?ref=rss",
            "site_title": null,
            "description": "Chris Sutton has hit out at Vaclav Cerny after he sprayed Celtic supporters with water during Sunday's derby clash with Rangers.",
            "enclosure_url": "https:\/\/www.glasgowtimes.co.uk\/resources\/images\/18648260\/",
            "width": 2400,
            "height": 1601
        },
        {
            "title": "The Green Brigade and the police: What happened, and have powers gone too far?",
            "date": "2025-03-17 21:00",
            "feed_title": "Glasgow Times | Celtic",
            "link": "https:\/\/www.glasgowtimes.co.uk\/sport\/25015468.green-brigade-police-happened-now\/?ref=rss",
            "site_title": null,
            "description": "What happened to make Police Scotland and Celtic ultras group The Green Brigade release statements about an incident on London Road before the Rangers game?",
            "enclosure_url": "https:\/\/www.glasgowtimes.co.uk\/resources\/images\/19216654\/",
            "width": 2400,
            "height": 1350
        },
        {
            "title": "Chris Sutton eviscerates Vaclav Cerny for 'silly' Rangers celebration after Celtic fan soaking ignores pre derby warning",
            "date": "2025-03-17 21:00",
            "feed_title": "Daily Record - Celtic FC",
            "link": "https:\/\/www.dailyrecord.co.uk\/sport\/football\/football-news\/sutton-cerny-celebration-rangers-celtic-34878767",
            "site_title": null,
            "description": "The former Celtic striker reckons things could have escalated on the Parkhead terraces after the actions of the winger",
            "enclosure_url": "https:\/\/i2-prod.dailyrecord.co.uk\/incoming\/article34879604.ece\/ALTERNATES\/s615\/0_Blackburn-Rovers-v-Derby-County-Sky-Bet-Championship-Ewood-Park.jpg",
            "width": 615,
            "height": 409
        },
        {
            "title": "Carter-Vickers lifts lid on costly moment that led to Rangers' winner vs Celtic",
            "date": "2025-03-17 20:45",
            "feed_title": "Glasgow Times | Celtic",
            "link": "https:\/\/www.glasgowtimes.co.uk\/sport\/25015492.carter-vickers-moment-led-igamane-goal-vs-celtic\/?ref=rss",
            "site_title": null,
            "description": "Cameron Carter-Vickers has lifted the lid on his missed header that led to Rangers' winner at Celtic Park on Sunday.",
            "enclosure_url": "https:\/\/www.glasgowtimes.co.uk\/resources\/images\/19217449\/",
            "width": 2400,
            "height": 1730
        },
        {
            "title": "Vaclav Cerny could have 'started a riot' with wild Celtic celebration as Rangers hero gifts winger one excuse",
            "date": "2025-03-17 20:16",
            "feed_title": "Daily Record - Celtic FC",
            "link": "https:\/\/www.dailyrecord.co.uk\/sport\/football\/football-news\/cerny-riot-rangers-celtic-fans-34879498",
            "site_title": null,
            "description": "The actions of the 27-year-old sparked a heated reaction from the home fans at Celtic Park after the late winner for Rangers",
            "enclosure_url": "https:\/\/i2-prod.dailyrecord.co.uk\/sport\/football\/football-news\/article34879537.ece\/ALTERNATES\/s615\/0_Screenshot-2025-03-17-at-200700.png",
            "width": 615,
            "height": 409
        },
        {
            "title": "Celtic on alert after Fabrizio Romano update opens door to transfer windfall",
            "date": "2025-03-17 20:14",
            "feed_title": "Glasgow Times | Celtic",
            "link": "https:\/\/www.glasgowtimes.co.uk\/sport\/25015478.celtic-alert-fabrizio-romano-transfer-update\/?ref=rss",
            "site_title": null,
            "description": "Celtic are on alert after Fabrizio Romano provided an update on the future of Jeremie Frimpong.",
            "enclosure_url": "https:\/\/www.glasgowtimes.co.uk\/resources\/images\/19217419\/",
            "width": 2400,
            "height": 1600
        },
        {
            "title": "Celtic to speak to police after fans denied match entry",
            "date": "2025-03-17 20:09",
            "feed_title": "BBC Sport",
            "link": "https:\/\/www.bbc.com\/news\/articles\/cy83248pnlro",
            "site_title": null,
            "description": "The club said it had received complaints from supporters about policing at the Old Firm game.",
            "enclosure_url": "https:\/\/ichef.bbci.co.uk\/ace\/standard\/240\/cpsprodpb\/e05c\/live\/98f5ef40-0365-11f0-a978-1107cece5934.jpg",
            "width": 240,
            "height": 134
        },
        {
            "title": "15 Celtic stars and 13 Rangers aces called up for international duty as two gear up for Scotland's Nations League play-off",
            "date": "2025-03-17 20:00",
            "feed_title": "GlasgowWorld Celtic",
            "link": "https:\/\/www.glasgowworld.com\/sport\/football\/15-celtic-stars-13-rangers-aces-international-duty-scotland-nations-league-play-off-5038057",
            "site_title": null,
            "description": "Every Celtic and Rangers player away on international duty during the domestic break",
            "enclosure_url": "https:\/\/www.glasgowworld.com\/jpim-static\/image\/2025\/03\/17\/18\/43\/What-is-your-favourite-Andy-Goram-moment-(22).jpeg?width=600&amp;auto=webp&amp;crop=3:2&amp;quality=70",
            "width": 600,
            "height": 502
        },
        {
            "title": "Celtic linked with striker who has 'huge potential' as part of \u00a310m Kyogo reinvestment",
            "date": "2025-03-17 20:00",
            "feed_title": "GlasgowWorld Celtic",
            "link": "https:\/\/www.glasgowworld.com\/sport\/football\/celtic\/celtic-linked-with-striker-who-has-huge-potential-as-part-of-ps10m-kyogo-reinvestment-5037836",
            "site_title": null,
            "description": "The Hoops will have money to spend in the summer transfer window but one target is reportedly also on the radar of some English clubs.",
            "enclosure_url": "https:\/\/www.glasgowworld.com\/jpim-static\/image\/2025\/02\/17\/9\/44\/GettyImages-2194555577.jpeg?width=600&amp;auto=webp&amp;crop=3:2&amp;quality=70",
            "width": 600,
            "height": 428
        },
        {
            "title": "Herba Guirassy a Celtic transfer 'target' as Leeds United battled for \u00a38.4m winger",
            "date": "2025-03-17 19:45",
            "feed_title": "Daily Record - Celtic FC",
            "link": "https:\/\/www.dailyrecord.co.uk\/sport\/football\/football-transfer-news\/herba-guirassy-celtic-transfer-target-34879378",
            "site_title": null,
            "description": "The French teenager has enjoyed a breakthrough season so far in Ligue 1",
            "enclosure_url": "https:\/\/i2-prod.dailyrecord.co.uk\/incoming\/article34879411.ece\/ALTERNATES\/s615\/1_herba.jpg",
            "width": 615,
            "height": 409
        },
        {
            "title": "Celtic 'raise concerns' after Vaclav Cerny incident in statement after police complaint",
            "date": "2025-03-17 19:44",
            "feed_title": "Daily Express :: Celtic Feed",
            "link": "https:\/\/www.express.co.uk\/sport\/football\/2028571\/Celtic-Rangers-Vaclav-Cerny-police-statement",
            "site_title": null,
            "description": "<a href=\"https:\/\/www.express.co.uk\/sport\/football\/2028571\/Celtic-Rangers-Vaclav-Cerny-police-statement\"><img src=\"https:\/\/cdn.images.express.co.uk\/img\/dynamic\/67\/590x\/2028571_1.jpg\"><\/a><br><br>Celtic have released a statement confirming they have raised concerns with authorities.",
            "enclosure_url": "https:\/\/cdn.images.express.co.uk\/img\/dynamic\/67\/590x\/2028571_1.jpg",
            "width": 590,
            "height": 369
        },
        {
            "title": "Ange Postecoglou Celtic signing wins first trophy since Parkhead exit",
            "date": "2025-03-17 19:21",
            "feed_title": "Glasgow Times | Celtic",
            "link": "https:\/\/www.glasgowtimes.co.uk\/sport\/25015455.postecoglou-signing-wins-first-trophy-since-celtic-exit\/?ref=rss",
            "site_title": null,
            "description": "Alexandro Bernabei has won his first trophy since leaving Celtic.",
            "enclosure_url": "https:\/\/www.glasgowtimes.co.uk\/resources\/images\/19217377\/",
            "width": 2400,
            "height": 1472
        },
        {
            "title": "Celtic release statement on Vaclav Cerny incident and 'policing operation'",
            "date": "2025-03-17 18:47",
            "feed_title": "Glasgow Times | Celtic",
            "link": "https:\/\/www.glasgowtimes.co.uk\/sport\/25015435.celtic-speak-cerny-incident-policing-operation\/?ref=rss",
            "site_title": null,
            "description": "Celtic have this evening released a statement regarding events both before and during the club's clash with Rangers yesterday.",
            "enclosure_url": "https:\/\/www.glasgowtimes.co.uk\/resources\/images\/19217332\/",
            "width": 2400,
            "height": 1482
        },
        {
            "title": "Celtic 'raise concerns' over Vaclav Cerny's Rangers celebration with authorities as Green Brigade lockout addressed",
            "date": "2025-03-17 18:35",
            "feed_title": "Daily Record - Celtic FC",
            "link": "https:\/\/www.dailyrecord.co.uk\/sport\/football\/football-news\/celtic-raise-concerns-over-vaclav-34879191",
            "site_title": null,
            "description": "The Hoops' have broken their silence on the flashpoint following Hamza Igamane's late winner at Celtic Park",
            "enclosure_url": "https:\/\/i2-prod.dailyrecord.co.uk\/sport\/football\/football-news\/article34871752.ece\/ALTERNATES\/s615\/0_Screenshot-2025-03-16-at-155819.png",
            "width": 615,
            "height": 409
        },
        {
            "title": "Cameron Carter-Vickers delivers verdict on Maik Nawrocki's display vs Rangers",
            "date": "2025-03-17 18:02",
            "feed_title": "Glasgow Times | Celtic",
            "link": "https:\/\/www.glasgowtimes.co.uk\/sport\/25015373.carter-vickers-verdict-nawrockis-display-vs-rangers\/?ref=rss",
            "site_title": null,
            "description": "Cameron Carter-Vickers says Maik Nawrocki played well for Celtic against Rangers on Sunday despite a 3-2 defeat.",
            "enclosure_url": "https:\/\/www.glasgowtimes.co.uk\/resources\/images\/19211820\/",
            "width": 2400,
            "height": 1453
        },
        {
            "title": "Brendan Rodgers outlines the Celtic sub who made a 'difference' vs Rangers",
            "date": "2025-03-17 17:37",
            "feed_title": "Glasgow Times | Celtic",
            "link": "https:\/\/www.glasgowtimes.co.uk\/sport\/25015319.rodgers-outlines-celtic-sub-made-difference-vs-rangers\/?ref=rss",
            "site_title": null,
            "description": "Celtic manager Brendan Rodgers says Yang Hyun-jun made a positive difference for his side off the bench against Rangers on Sunday.",
            "enclosure_url": "https:\/\/www.glasgowtimes.co.uk\/resources\/images\/19187758\/",
            "width": 2400,
            "height": 1730
        },
        {
            "title": "Danish pundit 'certain' long-term Celtic target will be on the move this summer",
            "date": "2025-03-17 17:13",
            "feed_title": "Glasgow Times | Celtic",
            "link": "https:\/\/www.glasgowtimes.co.uk\/sport\/25015213.pundit-certain-long-term-celtic-target-will-move\/?ref=rss",
            "site_title": null,
            "description": "Danish pundit Peter Sorensen is certain Celtic transfer target Mathias Kvistgaarden will depart Brondby this summer.",
            "enclosure_url": "https:\/\/www.glasgowtimes.co.uk\/resources\/images\/19217003\/",
            "width": 962,
            "height": 641
        },
        {
            "title": "Celtic star's Old Firm absence vs Rangers proves how 'valuable' he is as Rodgers points to lack of fluidity",
            "date": "2025-03-17 17:00",
            "feed_title": "GlasgowWorld Celtic",
            "link": "https:\/\/www.glasgowworld.com\/sport\/football\/celtic\/celtic-star-old-firm-absence-rangers-brendan-rodgers-fluidity-5036920",
            "site_title": null,
            "description": "Celtic were without captain Callum McGregor for Sunday\u2019s Old Firm loss at home to Rangers in the Scottish Premiership",
            "enclosure_url": "https:\/\/www.glasgowworld.com\/jpim-static\/image\/2025\/01\/01\/14\/28\/RC1_(4).jpeg?width=600&amp;auto=webp&amp;crop=3:2&amp;quality=70",
            "width": 600,
            "height": 366
        }
    ]
}